blob_reader/__init__.py
blob_reader/block.py
blob_reader-1.0.0.dist-info/METADATA
blob_reader-1.0.0.dist-info/WHEEL
blob_reader-1.0.0.dist-info/RECORD
