Metadata-Version: 2.1
Name: blob-reader
Version: 1.0.0
Summary: Easily _read binary data in a Pythonic way
License: MIT
Author: Steven 'KaReL' Van Ingelgem
Author-email: steven@vaningelgem.be
Requires-Python: >=3.7
Classifier: License :: OSI Approved :: MIT License
Classifier: Programming Language :: Python :: 3
Classifier: Programming Language :: Python :: 3.7
Classifier: Programming Language :: Python :: 3.8
Classifier: Programming Language :: Python :: 3.9
Classifier: Programming Language :: Python :: 3.10
Classifier: Programming Language :: Python :: 3.11
Project-URL: Source Code, https://github.com/svaningelgem/blob_reader
